simvue/__init__.py
simvue/api/__init__.py
simvue/api/objects/__init__.py
simvue/api/objects/administrator/__init__.py
simvue/api/objects/administrator/tenant.py
simvue/api/objects/administrator/user.py
simvue/api/objects/alert/__init__.py
simvue/api/objects/alert/base.py
simvue/api/objects/alert/events.py
simvue/api/objects/alert/fetch.py
simvue/api/objects/alert/metrics.py
simvue/api/objects/alert/user.py
simvue/api/objects/artifact/__init__.py
simvue/api/objects/artifact/base.py
simvue/api/objects/artifact/fetch.py
simvue/api/objects/artifact/file.py
simvue/api/objects/artifact/object.py
simvue/api/objects/base.py
simvue/api/objects/events.py
simvue/api/objects/folder.py
simvue/api/objects/grids.py
simvue/api/objects/metrics.py
simvue/api/objects/run.py
simvue/api/objects/stats.py
simvue/api/objects/storage/__init__.py
simvue/api/objects/storage/base.py
simvue/api/objects/storage/fetch.py
simvue/api/objects/storage/file.py
simvue/api/objects/storage/s3.py
simvue/api/objects/tag.py
simvue/api/request.py
simvue/api/url.py
simvue/bin/__init__.py
simvue/bin/sender.py
simvue/client.py
simvue/config/__init__.py
simvue/config/files.py
simvue/config/parameters.py
simvue/config/simvue_config_schema.json
simvue/config/user.py
simvue/converters.py
simvue/eco/__init__.py
simvue/eco/api_client.py
simvue/eco/config.py
simvue/eco/emissions_monitor.py
simvue/exception.py
simvue/executor.py
simvue/factory/__init__.py
simvue/factory/dispatch/__init__.py
simvue/factory/dispatch/base.py
simvue/factory/dispatch/direct.py
simvue/factory/dispatch/queued.py
simvue/handler.py
simvue/metadata.py
simvue/metrics.py
simvue/models.py
simvue/pynvml.py
simvue/run.py
simvue/sender/__init__.py
simvue/sender/actions.py
simvue/sender/base.py
simvue/serialization.py
simvue/simvue_types.py
simvue/system.py
simvue/utilities.py
simvue/version.py
simvue-2.3.1.dist-info/METADATA
simvue-2.3.1.dist-info/WHEEL
simvue-2.3.1.dist-info/entry_points.txt
simvue-2.3.1.dist-info/licenses/LICENSE
simvue-2.3.1.dist-info/RECORD
