Metadata-Version: 2.4
Name: simvue
Version: 2.3.1
Summary: Simulation tracking and monitoring
License: Apache v2
License-File: LICENSE
Keywords: tracking,monitoring,metrics,alerting,metrics-gathering
Author: Simvue Development Team
Author-email: info@simvue.io
Requires-Python: >=3.10,<3.15
Classifier: Development Status :: 5 - Production/Stable
Classifier: Intended Audience :: Science/Research
Classifier: License :: OSI Approved :: Apache Software License
Classifier: Natural Language :: English
Classifier: Operating System :: Unix
Classifier: Operating System :: Microsoft :: Windows
Classifier: Programming Language :: Python :: 3
Classifier: Programming Language :: Python :: 3.10
Classifier: Programming Language :: Python :: 3.11
Classifier: Programming Language :: Python :: 3.12
Classifier: Programming Language :: Python :: 3.13
Classifier: Programming Language :: Python :: 3.14
Classifier: Topic :: Scientific/Engineering
Classifier: Topic :: System :: Monitoring
Classifier: Topic :: Utilities
Classifier: Typing :: Typed
Provides-Extra: plot
Requires-Dist: click (>=8.1.8,<9.0.0)
Requires-Dist: deepmerge (>=2.0,<3.0)
Requires-Dist: email-validator (>=2.2.0,<3.0.0)
Requires-Dist: flatdict (>=4.0.1,<5.0.0)
Requires-Dist: geocoder (>=1.38.1,<2.0.0)
Requires-Dist: gitpython (>=3.1.44,<4.0.0)
Requires-Dist: humanfriendly (>=10.0,<11.0)
Requires-Dist: matplotlib (>=3.10.0,<4.0.0) ; extra == "plot"
Requires-Dist: msgpack (>=1.1.0,<2.0.0)
Requires-Dist: numpy (>=2.0.0,<3.0.0)
Requires-Dist: pandas (>=2.2.3,<3.0.0)
Requires-Dist: plotly (>=6.0.0,<7.0.0) ; extra == "plot"
Requires-Dist: psutil (>=6.1.1,<7.0.0)
Requires-Dist: pydantic (>=2.11,<3.0.0)
Requires-Dist: pydantic-extra-types (>=2.10.5,<3.0.0)
Requires-Dist: pyjwt (>=2.10.1,<3.0.0)
Requires-Dist: pyyaml (>=6.0.2,<7.0.0)
Requires-Dist: randomname (>=0.2.1,<0.3.0)
Requires-Dist: requests (>=2.32.3,<3.0.0)
Requires-Dist: semver (>=3.0.4,<4.0.0)
Requires-Dist: tabulate (>=0.9.0,<0.10.0)
Requires-Dist: tenacity (>=9.0.0,<10.0.0)
Requires-Dist: toml (>=0.10.2,<0.11.0)
Requires-Dist: typing-extensions (>=4.12.2,<5.0.0) ; python_version < "3.11"
Project-URL: Documentation, https://docs.simvue.io
Project-URL: Homepage, https://simvue.io
Project-URL: Repository, https://github.com/simvue-io/python-api
